comfy-0.0.1.dist-info/metadata.json
comfy-0.0.1.dist-info/RECORD
comfy-0.0.1.dist-info/METADATA
comfy-0.0.1.dist-info/top_level.txt
comfy-0.0.1.dist-info/DESCRIPTION.rst
comfy-0.0.1.dist-info/WHEEL
comfy/fields.py
comfy/__init__.py
